clustersight/__init__.py
clustersight/cluster.py
clustersight-0.0.2.dist-info/METADATA
clustersight-0.0.2.dist-info/WHEEL
clustersight-0.0.2.dist-info/licenses/LICENSE
clustersight-0.0.2.dist-info/RECORD
