Metadata-Version: 2.1
Name: clustersight
Version: 0.0.2
Summary: A package to analyze and interpret categorical clustered data
Project-URL: Homepage, https://github.com/jboesen/clustersight
Project-URL: Bug Tracker, https://github.com/jboesen/clustersight/issues
Author-email: John Boesen <jmboesen@college.harvard.edu>
License-File: LICENSE
Classifier: Development Status :: 3 - Alpha
Classifier: Environment :: MacOS X
Classifier: Framework :: IPython
Classifier: Framework :: Jupyter
Classifier: Intended Audience :: Developers
Classifier: Intended Audience :: Science/Research
Classifier: License :: OSI Approved :: MIT License
Classifier: Natural Language :: English
Classifier: Programming Language :: Python :: 3
Classifier: Programming Language :: Python :: 3.7
Classifier: Programming Language :: Python :: 3.8
Classifier: Programming Language :: Python :: 3.9
Classifier: Programming Language :: Python :: 3.10
Classifier: Programming Language :: Python :: 3.11
Classifier: Programming Language :: Python :: 3.12
Classifier: Topic :: Scientific/Engineering
Classifier: Topic :: Scientific/Engineering :: Artificial Intelligence
Classifier: Topic :: Scientific/Engineering :: Information Analysis
Classifier: Topic :: Scientific/Engineering :: Visualization
Classifier: Topic :: Software Development :: Libraries :: Python Modules
Classifier: Topic :: System :: Clustering
Requires-Python: >=3.6
Requires-Dist: dtreeviz>=2.2.0
Requires-Dist: ipython>=8.8.0
Requires-Dist: ipywidgets>=7.7.1
Requires-Dist: numpy>=1.22.0
Requires-Dist: pandas>=1.5.2
Requires-Dist: plotly>=5.11.0
Requires-Dist: scikit-learn>=0.0.post1
